iecasdmx/__init__.py
iecasdmx/funciones.py
iecasdmx/main.py
iecasdmx/configuracion/actividades.yaml
iecasdmx/configuracion/ejecucion.yaml
iecasdmx/configuracion/global.yaml
iecasdmx/configuracion/plantilla_actividad.yaml
iecasdmx/ieca/__init__.py
iecasdmx/ieca/actividad.py
iecasdmx/ieca/consulta.py
iecasdmx/ieca/datos.py
iecasdmx/ieca/jerarquia.py
iecasdmx/utiles/__init__.py
iecasdmx/utiles/embellecedor_metadatos.py
iecasdmx/utiles/traducir.py
iecasdmx/utiles/validador.py
iecasdmx/utiles/metadatos/__init__.py
iecasdmx-0.2.0.dist-info/METADATA
iecasdmx-0.2.0.dist-info/WHEEL
iecasdmx-0.2.0.dist-info/top_level.txt
iecasdmx-0.2.0.dist-info/RECORD
