Metadata-Version: 2.1
Name: iecasdmx
Version: 0.2.0
Summary: Transformación de datos y metadatos desde el IECA hacia SDMX
Home-page: https://github.com/frapercan/IECA2SDMX
Author: frapercan
Author-email: frapercan1@alum.us.es
License: MIT
Classifier: Development Status :: 2 - Pre-Alpha
Classifier: License :: OSI Approved :: MIT License
Classifier: Programming Language :: Python :: 3.8
